nixpack_package-0.1.dist-info/METADATA
nixpack_package-0.1.dist-info/WHEEL
nixpack_package-0.1.dist-info/entry_points.txt
nixpack_package/__init__.py
nixpack_package/server.py
nixpack_package-0.1.dist-info/RECORD
